{"docstore/data":{"0705d9e7-06bf-491c-b8fb-c29ee7ed2a22":{"indexId":"0705d9e7-06bf-491c-b8fb-c29ee7ed2a22","nodesDict":{"108ae684-bd34-41a7-89a6-2ea79c516de5":{"id_":"108ae684-bd34-41a7-89a6-2ea79c516de5","metadata":{"url":"https://www.mapquest.com/us/pennsylvania/priority-express-courier-2280900"},"excludedEmbedMetadataKeys":[],"excludedLlmMetadataKeys":[],"relationships":{"SOURCE":{"nodeId":"b2c81a6a-dfa6-4bd9-b32c-e60d5bb093bb","metadata":{"url":"https://www.mapquest.com/us/pennsylvania/priority-express-courier-2280900"},"hash":"aJxE5vGo/92NFUdxPxMYKDOrBB7r63JB2Gi7t8JM/x8="}},"text":"Advertisement\nAdvertisement\n© 2024 Mapquest Holdings LLC© HEREPrivacyLegalAbout Our AdsDo Not Sell or Share my Personal Data\n100 m\nSearch MapQuest\nHotels\nFood\nShopping\nCoffee\nGrocery\nGas\nPriority Express Courier\n+1 (610) 245-2300\nWebsite\nMore\nDirections\nAdvertisement\n12 Creek Pkwy\nMarcus Hook, PA 19061\n+1 (610) 245-2300\nhttp://priorityexpress.com\nPriority Express Courier is a reputable courier service based in Marcus Hook, PA, specializing in efficient and reliable package delivery.\nWith a focus on prompt and secure transportation, the company caters to a wide range of clients seeking timely delivery solutions in the local area.\nMore\nAlso at this address\nCustomer America Inc\nSOLID Surface Care, Inc\nLincare\nHEALTH CARE SOLUTIONS\nOwn this business?\nClaim it\nSee a problem?\nLet us know\nYou might also like\nCourier or messenger service, Delivery service, vehicular, Personal shopping service\nAction Port Courier Corp\nAction Port Courier is a reliable courier service based in Springfield, PA, specializing in fast and efficient delivery solutions for businesses and individuals. With a focus on timely deliveries and secure handling of packages, they offer a range of shipping options to meet various needs. Utilizing advanced tracking technology and a dedicated team of professionals, Action Port Courier ensures that packages are delivered safely and on time. Their commitment to customer satisfaction and attention to detail make them a trusted choice for all shipping needs in the Springfield area. Generated from their business information\nCourier or messenger service, Personal shopping service\nSame Day Delivery\nSame Day Delivery is a local business in Essington, PA that specializes in providing prompt delivery services to its customers. With a focus on efficiency and reliability, the company ensures that packages and goods reach their destinations on the same day they are ordered. Generated from their business information\nCourier or messenger service, Personal shopping service, Services, nec, nec\nDedicated Logistics Service Inc\nDedicated Logistics Services (DLS) is a leading transportation company based in Darby Twp, PA, offering a wide range of services to clients. With a focus on cost-effective efficiencies and customized solutions, DLS provides a competitive service advantage through dedicated project managers, well-trained drivers, and real-time tracking and updates. As a proud member of the logistics industry, DLS is committed to delivering consistent on-time service and added value to its clients. With a dynamic transportation blueprint, DLS creates tailored solutions that meet the unique needs of businesses, ensuring lowered costs and efficient operations.Generated from the website\nUnited States›\nPennsylvania›\nMarcus Hook›\nPriority Express Courier\nPartial Data by Foursquare.\nAdvertisement","textTemplate":"","endCharIdx":2832,"metadataSeparator":"\n","type":"TEXT","hash":"LsS9v0gGAAh9etgmIeOcklhZJhWaZBwcUwsextv4nBA="}},"type":"simple_dict"}}}